odoo9_addon_sale_commission-9.0.1.1.0-py2.7-nspkg.pth
odoo9_addon_sale_commission-9.0.1.1.0.dist-info/DESCRIPTION.rst
odoo9_addon_sale_commission-9.0.1.1.0.dist-info/METADATA
odoo9_addon_sale_commission-9.0.1.1.0.dist-info/RECORD
odoo9_addon_sale_commission-9.0.1.1.0.dist-info/WHEEL
odoo9_addon_sale_commission-9.0.1.1.0.dist-info/metadata.json
odoo9_addon_sale_commission-9.0.1.1.0.dist-info/namespace_packages.txt
odoo9_addon_sale_commission-9.0.1.1.0.dist-info/top_level.txt
odoo_addons/sale_commission/README.rst
odoo_addons/sale_commission/__init__.py
odoo_addons/sale_commission/__openerp__.py
odoo_addons/sale_commission/demo/sale_agent_demo.xml
odoo_addons/sale_commission/i18n/am.po
odoo_addons/sale_commission/i18n/ar.po
odoo_addons/sale_commission/i18n/bg.po
odoo_addons/sale_commission/i18n/bs.po
odoo_addons/sale_commission/i18n/ca.po
odoo_addons/sale_commission/i18n/cs.po
odoo_addons/sale_commission/i18n/da.po
odoo_addons/sale_commission/i18n/de.po
odoo_addons/sale_commission/i18n/el_GR.po
odoo_addons/sale_commission/i18n/en_GB.po
odoo_addons/sale_commission/i18n/es.po
odoo_addons/sale_commission/i18n/es_CR.po
odoo_addons/sale_commission/i18n/es_EC.po
odoo_addons/sale_commission/i18n/es_MX.po
odoo_addons/sale_commission/i18n/es_VE.po
odoo_addons/sale_commission/i18n/et.po
odoo_addons/sale_commission/i18n/eu.po
odoo_addons/sale_commission/i18n/fi.po
odoo_addons/sale_commission/i18n/fr.po
odoo_addons/sale_commission/i18n/fr_CH.po
odoo_addons/sale_commission/i18n/gl.po
odoo_addons/sale_commission/i18n/hr.po
odoo_addons/sale_commission/i18n/hr_HR.po
odoo_addons/sale_commission/i18n/it.po
odoo_addons/sale_commission/i18n/ja.po
odoo_addons/sale_commission/i18n/lt.po
odoo_addons/sale_commission/i18n/lv.po
odoo_addons/sale_commission/i18n/mk.po
odoo_addons/sale_commission/i18n/mn.po
odoo_addons/sale_commission/i18n/nb.po
odoo_addons/sale_commission/i18n/nb_NO.po
odoo_addons/sale_commission/i18n/nl.po
odoo_addons/sale_commission/i18n/nl_BE.po
odoo_addons/sale_commission/i18n/pl.po
odoo_addons/sale_commission/i18n/pt.po
odoo_addons/sale_commission/i18n/pt_BR.po
odoo_addons/sale_commission/i18n/pt_PT.po
odoo_addons/sale_commission/i18n/ro.po
odoo_addons/sale_commission/i18n/ru.po
odoo_addons/sale_commission/i18n/sale_commission.pot
odoo_addons/sale_commission/i18n/sk.po
odoo_addons/sale_commission/i18n/sl.po
