Metadata-Version: 2.0
Name: odoo9-addon-sale-commission
Version: 9.0.1.1.0
Summary: Sales commissions
Home-page: UNKNOWN
Author: Pexego, Savoir-faire linux, Avanzosc, Abstract, Serv. Tecnol. Avanzados - Pedro M. Baeza, Odoo Community Association (OCA)
Author-email: support@odoo-community.org
License: AGPL-3
Platform: UNKNOWN
Classifier: Programming Language :: Python
Classifier: Framework :: Odoo
Classifier: License :: OSI Approved :: GNU Affero General Public License v3
Requires-Python: ~=2.7
Requires-Dist: odoo (<9.1a,>=9.0a)
